{
  "content": null,
  "embeds": [
    {
      "description": "⠀ ⠀ ⠀ ⠀ ⠀ ⠀  ⠀ ⠀ ╔ ⇒<a:6956_Alphabet_T:834133031052115968><a:7273_Alphabet_E:833813061293965353><a:5529_Alphabet_M:834133057405059123><a:5132_Alphabet_P:834133142066954241>  <a:9850_Alphabet_B:833807987885342733><a:7407_Alphabet_A:833807997989552168><a:5498_Alphabet_N:778279421122707478>⇐ ╗⠀ ⠀ ⠀ ⠀ ⠀ ⠀ ⠀ ⠀ ⠀ ⠀",
      "color": 0
    },
    {
      "title": "⠀  ︵︵︵︵︵︵︵︵︵︵︵︵︵︵︵︵︵︵\n↪ Многоуважаемый пользователь сервера ↩ \n⠀  ︶︶︶︶︶︶︶︶︶︶︶︶︶︶︶︶︶︶\n⠀  ⠀  ⠀  ⠀  ⠀  ⠀  ⠀      ⤋⤋⤋\n                      ✞≪ 𝕺𝖚𝖗 𝕹𝖊𝖜 𝖂𝖔𝖗𝖑𝖉 ≫✞",
      "description": "> **✬** Вам выдали __временный__ **бан** По причине: {reason}. Время бана: {time}. <a:9441uncheckraveninha:834149910801678417>\n> **✬** По его окончании, с вас автоматически снимется **бан**, и вы сможете вернутся на сервер по *__[ссылке]({link})__.* <a:6233verifyedited:834149775380447292>",
      "color": 0,
      "image": {
        "url": "https://i.gifer.com/fzm0.gif"
      },
      "thumbnail": {
        "url": "https://i.gifer.com/7V9.gif"
      }
    },
    {
      "description": "⠀ ⠀ ⠀ ⠀ ⠀ ⠀  ⠀ ⠀ ╚ ⇒<a:6956_Alphabet_T:834133031052115968><a:7273_Alphabet_E:833813061293965353><a:5529_Alphabet_M:834133057405059123><a:5132_Alphabet_P:834133142066954241>  <a:9850_Alphabet_B:833807987885342733><a:7407_Alphabet_A:833807997989552168><a:5498_Alphabet_N:778279421122707478>⇐ ╝⠀ ⠀ ⠀ ⠀ ⠀ ⠀ ⠀ ⠀ ⠀ ⠀",
      "color": 0
    }
  ]
}